{"title":"Roy Mwavita | Data Analyst & M&E Specialist","markdown":{"yaml":{"title":"Roy Mwavita | Data Analyst & M&E Specialist","description":"Portfolio of dashboards, R Shiny apps, and monitoring & evaluation projects in public health and development programs."},"headingText":"👤 About Me","containsRefs":false,"markdown":"\n\n---\n\n\n\n::: {.grid}\n\n::: {.g-col-12 .g-col-md-6}\n\n::: {.card}\n\nResearch Data Analyst & Monitoring and Evaluation Professional with over three years’ experience in managing, analyzing, and reporting complex datasets across health research, child welfare, and USAID-funded programs. \n\nExperienced in supporting studies involving 6,500+ beneficiaries, improving reporting efficiency by 40%, reducing manual data validation workload by 60%, and developing automated analytics solutions using R, R-Shiny, Python, Excel, KoboToolbox, and Power BI.  \n\nMy work focuses on improving data quality, automating reporting systems, and building tools that support evidence-based decision-making in development programs.\n\n\n:::\n\n:::\n\n::: {.g-col-12 .g-col-md-6}\n\n### 🧠 Skills\n\n::: {.card}\n\n**Data Analysis & Programming**\n- R (tidyverse, Shiny, ggplot2, highcharter)\n- Data cleaning & transformation\n- Statistical reporting\n\n**Monitoring & Evaluation**\n- M&E frameworks\n- Indicator tracking systems\n- Data quality assessment\n\n**Data Tools**\n- KoboToolbox\n- Excel advanced analytics\n- Git & GitHub (basic version control)\n\n**Visualization & Reporting**\n- Interactive dashboards\n- Quarto & R Markdown reporting\n- Automated reporting systems\n\n\n:::\n:::\n:::\n\n\n\n---\n\n## 🚀 Explore My Work\n\n::: {.grid}\n\n::: {.g-col-12 .g-col-md-6}\n\n::: {.card}\n\n### 📊 Dashboards\n\nInteractive R Shiny dashboards for monitoring program performance and tracking key indicators in real time.\n\n[View Dashboards →](dashboards.qmd)\n\n:::\n\n:::\n\n::: {.g-col-12 .g-col-md-6}\n\n::: {.card}\n\n### 📘 R Toolkit Digest\n\nA curated series of practical R tutorials and applied data workflows for real-world MEAL and analytics work.\n\n[Read Digest →](digest.qmd)\n\n:::\n\n:::\n\n::: {.g-col-12 .g-col-md-6}\n\n::: {.card}\n\n### 📰 Newsletter\n\nInsights, learning notes, and reflections on data, monitoring, and evaluation practice.\n\n[Read Newsletter →](newsletter.qmd)\n\n:::\n\n:::\n\n::: {.g-col-12 .g-col-md-6}\n\n::: {.card}\n\n### 🧩 Projects\n\nA collection of data systems, tools, and analytical solutions I have developed.\n\n[View Projects →](projects.qmd)\n\n:::\n\n:::\n\n:::\n\n---\n\n## 📫 Contact\n\n::: {.card}\n\n- 📧 lennicroy@gmail.com  \n- 🔗 [LinkedIn→](\"https://www.linkedin.com/in/roy-mwavita-495b50220/\")\n- 🔗 [GitHub→](\"https://github.com/roy-mwavita0/\")\n\n```{=html}\n<a href=\"files/CV_Roy Mwavita.pdf\" target=\"_blank\">\n  <button style=\"padding:8px 14px; border:none; border-radius:8px; background:#2c3e50; color:white; cursor:pointer;\">\n    📥 Download CV\n  </button>\n</a>\n\n```\n\n:::","srcMarkdownNoYaml":"\n\n---\n\n## 👤 About Me\n\n\n::: {.grid}\n\n::: {.g-col-12 .g-col-md-6}\n\n::: {.card}\n\nResearch Data Analyst & Monitoring and Evaluation Professional with over three years’ experience in managing, analyzing, and reporting complex datasets across health research, child welfare, and USAID-funded programs. \n\nExperienced in supporting studies involving 6,500+ beneficiaries, improving reporting efficiency by 40%, reducing manual data validation workload by 60%, and developing automated analytics solutions using R, R-Shiny, Python, Excel, KoboToolbox, and Power BI.  \n\nMy work focuses on improving data quality, automating reporting systems, and building tools that support evidence-based decision-making in development programs.\n\n\n:::\n\n:::\n\n::: {.g-col-12 .g-col-md-6}\n\n### 🧠 Skills\n\n::: {.card}\n\n**Data Analysis & Programming**\n- R (tidyverse, Shiny, ggplot2, highcharter)\n- Data cleaning & transformation\n- Statistical reporting\n\n**Monitoring & Evaluation**\n- M&E frameworks\n- Indicator tracking systems\n- Data quality assessment\n\n**Data Tools**\n- KoboToolbox\n- Excel advanced analytics\n- Git & GitHub (basic version control)\n\n**Visualization & Reporting**\n- Interactive dashboards\n- Quarto & R Markdown reporting\n- Automated reporting systems\n\n\n:::\n:::\n:::\n\n\n\n---\n\n## 🚀 Explore My Work\n\n::: {.grid}\n\n::: {.g-col-12 .g-col-md-6}\n\n::: {.card}\n\n### 📊 Dashboards\n\nInteractive R Shiny dashboards for monitoring program performance and tracking key indicators in real time.\n\n[View Dashboards →](dashboards.qmd)\n\n:::\n\n:::\n\n::: {.g-col-12 .g-col-md-6}\n\n::: {.card}\n\n### 📘 R Toolkit Digest\n\nA curated series of practical R tutorials and applied data workflows for real-world MEAL and analytics work.\n\n[Read Digest →](digest.qmd)\n\n:::\n\n:::\n\n::: {.g-col-12 .g-col-md-6}\n\n::: {.card}\n\n### 📰 Newsletter\n\nInsights, learning notes, and reflections on data, monitoring, and evaluation practice.\n\n[Read Newsletter →](newsletter.qmd)\n\n:::\n\n:::\n\n::: {.g-col-12 .g-col-md-6}\n\n::: {.card}\n\n### 🧩 Projects\n\nA collection of data systems, tools, and analytical solutions I have developed.\n\n[View Projects →](projects.qmd)\n\n:::\n\n:::\n\n:::\n\n---\n\n## 📫 Contact\n\n::: {.card}\n\n- 📧 lennicroy@gmail.com  \n- 🔗 [LinkedIn→](\"https://www.linkedin.com/in/roy-mwavita-495b50220/\")\n- 🔗 [GitHub→](\"https://github.com/roy-mwavita0/\")\n\n```{=html}\n<a href=\"files/CV_Roy Mwavita.pdf\" target=\"_blank\">\n  <button style=\"padding:8px 14px; border:none; border-radius:8px; background:#2c3e50; color:white; cursor:pointer;\">\n    📥 Download CV\n  </button>\n</a>\n\n```\n\n:::"},"formats":{"html":{"identifier":{"display-name":"HTML","target-format":"html","base-format":"html"},"execute":{"fig-width":7,"fig-height":5,"fig-format":"retina","fig-dpi":96,"df-print":"default","error":false,"eval":true,"cache":null,"freeze":false,"echo":true,"output":true,"warning":true,"include":true,"keep-md":false,"keep-ipynb":false,"ipynb":null,"enabled":null,"daemon":null,"daemon-restart":false,"debug":false,"ipynb-filters":[],"ipynb-shell-interactivity":null,"plotly-connected":true,"engine":"markdown"},"render":{"keep-tex":false,"keep-typ":false,"keep-source":false,"keep-hidden":false,"prefer-html":false,"output-divs":true,"output-ext":"html","fig-align":"default","fig-pos":null,"fig-env":null,"code-fold":"none","code-overflow":"scroll","code-link":false,"code-line-numbers":false,"code-tools":false,"tbl-colwidths":"auto","merge-includes":true,"inline-includes":false,"preserve-yaml":false,"latex-auto-mk":true,"latex-auto-install":true,"latex-clean":true,"latex-min-runs":1,"latex-max-runs":10,"latex-makeindex":"makeindex","latex-makeindex-opts":[],"latex-tlmgr-opts":[],"latex-input-paths":[],"latex-output-dir":null,"link-external-icon":false,"link-external-newwindow":false,"self-contained-math":false,"format-resources":[],"notebook-links":true},"pandoc":{"standalone":true,"wrap":"none","default-image-extension":"png","to":"html","css":["styles.css"],"toc":true,"output-file":"index.html"},"language":{"toc-title-document":"Table of contents","toc-title-website":"On this page","related-formats-title":"Other Formats","related-notebooks-title":"Notebooks","source-notebooks-prefix":"Source","other-links-title":"Other Links","code-links-title":"Code Links","launch-dev-container-title":"Launch Dev Container","launch-binder-title":"Launch Binder","article-notebook-label":"Article Notebook","notebook-preview-download":"Download Notebook","notebook-preview-download-src":"Download Source","notebook-preview-back":"Back to Article","manuscript-meca-bundle":"MECA Bundle","section-title-abstract":"Abstract","section-title-appendices":"Appendices","section-title-footnotes":"Footnotes","section-title-references":"References","section-title-reuse":"Reuse","section-title-copyright":"Copyright","section-title-citation":"Citation","appendix-attribution-cite-as":"For attribution, please cite this work as:","appendix-attribution-bibtex":"BibTeX citation:","appendix-view-license":"View License","title-block-author-single":"Author","title-block-author-plural":"Authors","title-block-affiliation-single":"Affiliation","title-block-affiliation-plural":"Affiliations","title-block-published":"Published","title-block-modified":"Modified","title-block-keywords":"Keywords","callout-tip-title":"Tip","callout-note-title":"Note","callout-warning-title":"Warning","callout-important-title":"Important","callout-caution-title":"Caution","code-summary":"Code","code-tools-menu-caption":"Code","code-tools-show-all-code":"Show All Code","code-tools-hide-all-code":"Hide All Code","code-tools-view-source":"View Source","code-tools-source-code":"Source Code","tools-share":"Share","tools-download":"Download","code-line":"Line","code-lines":"Lines","copy-button-tooltip":"Copy to Clipboard","copy-button-tooltip-success":"Copied!","repo-action-links-edit":"Edit this page","repo-action-links-source":"View source","repo-action-links-issue":"Report an issue","back-to-top":"Back to top","search-no-results-text":"No results","search-matching-documents-text":"matching documents","search-copy-link-title":"Copy link to search","search-hide-matches-text":"Hide additional matches","search-more-match-text":"more match in this document","search-more-matches-text":"more matches in this document","search-clear-button-title":"Clear","search-text-placeholder":"","search-detached-cancel-button-title":"Cancel","search-submit-button-title":"Submit","search-label":"Search","toggle-section":"Toggle section","toggle-sidebar":"Toggle sidebar navigation","toggle-dark-mode":"Toggle dark mode","toggle-reader-mode":"Toggle reader mode","toggle-navigation":"Toggle navigation","crossref-fig-title":"Figure","crossref-tbl-title":"Table","crossref-lst-title":"Listing","crossref-thm-title":"Theorem","crossref-lem-title":"Lemma","crossref-cor-title":"Corollary","crossref-prp-title":"Proposition","crossref-cnj-title":"Conjecture","crossref-def-title":"Definition","crossref-exm-title":"Example","crossref-exr-title":"Exercise","crossref-ch-prefix":"Chapter","crossref-apx-prefix":"Appendix","crossref-sec-prefix":"Section","crossref-eq-prefix":"Equation","crossref-lof-title":"List of Figures","crossref-lot-title":"List of Tables","crossref-lol-title":"List of Listings","environment-proof-title":"Proof","environment-remark-title":"Remark","environment-solution-title":"Solution","listing-page-order-by":"Order By","listing-page-order-by-default":"Default","listing-page-order-by-date-asc":"Oldest","listing-page-order-by-date-desc":"Newest","listing-page-order-by-number-desc":"High to Low","listing-page-order-by-number-asc":"Low to High","listing-page-field-date":"Date","listing-page-field-title":"Title","listing-page-field-description":"Description","listing-page-field-author":"Author","listing-page-field-filename":"File Name","listing-page-field-filemodified":"Modified","listing-page-field-subtitle":"Subtitle","listing-page-field-readingtime":"Reading Time","listing-page-field-wordcount":"Word Count","listing-page-field-categories":"Categories","listing-page-minutes-compact":"{0} min","listing-page-category-all":"All","listing-page-no-matches":"No matching items","listing-page-words":"{0} words","listing-page-filter":"Filter","draft":"Draft"},"metadata":{"lang":"en","fig-responsive":true,"quarto-version":"1.9.38","engines":[{"path":"C:\\Program Files\\Quarto\\share\\extension-subtrees\\julia-engine\\_extensions\\julia-engine\\julia-engine.js"}],"theme":"yeti","title":"Roy Mwavita | Data Analyst & M&E Specialist","description":"Portfolio of dashboards, R Shiny apps, and monitoring & evaluation projects in public health and development programs."},"extensions":{"book":{"multiFile":true}}}},"projectFormats":["html"]}